cmany-0.1.4-py3.8-nspkg.pth
c4/cmany/__init__.py
c4/cmany/architecture.py
c4/cmany/args.py
c4/cmany/build.py
c4/cmany/build_flags.py
c4/cmany/build_item.py
c4/cmany/build_type.py
c4/cmany/cmake.py
c4/cmany/combination_rules.py
c4/cmany/compiler.py
c4/cmany/conan.py
c4/cmany/conf.py
c4/cmany/err.py
c4/cmany/flags.py
c4/cmany/generator.py
c4/cmany/help.py
c4/cmany/main.py
c4/cmany/named_item.py
c4/cmany/project.py
c4/cmany/system.py
c4/cmany/util.py
c4/cmany/variant.py
c4/cmany/vsinfo.py
c4/cmany/conf/cmany.yml
c4/cmany/doc/build_items.txt
c4/cmany/doc/cmany.txt
c4/cmany/doc/dependencies.txt
c4/cmany/doc/excluding_builds.txt
c4/cmany/doc/flags.txt
c4/cmany/doc/index.txt
c4/cmany/doc/installing.txt
c4/cmany/doc/quick_tour.txt
c4/cmany/doc/reusing_arguments.txt
c4/cmany/doc/vs.txt
cmany-0.1.4.data/data/c4/cmany/CHANGELOG.md
cmany-0.1.4.data/data/c4/cmany/LICENSE.txt
cmany-0.1.4.data/data/c4/cmany/README.rst
cmany-0.1.4.data/data/c4/cmany/requirements.txt
cmany-0.1.4.data/data/c4/cmany/requirements_test.txt
cmany-0.1.4.data/data/c4/cmany/conf/cmany.yml
cmany-0.1.4.data/data/c4/cmany/doc/build_items.txt
cmany-0.1.4.data/data/c4/cmany/doc/cmany.txt
cmany-0.1.4.data/data/c4/cmany/doc/dependencies.txt
cmany-0.1.4.data/data/c4/cmany/doc/excluding_builds.txt
cmany-0.1.4.data/data/c4/cmany/doc/flags.txt
cmany-0.1.4.data/data/c4/cmany/doc/index.txt
cmany-0.1.4.data/data/c4/cmany/doc/installing.txt
cmany-0.1.4.data/data/c4/cmany/doc/quick_tour.txt
cmany-0.1.4.data/data/c4/cmany/doc/reusing_arguments.txt
cmany-0.1.4.data/data/c4/cmany/doc/vs.txt
cmany-0.1.4.dist-info/LICENSE.txt
cmany-0.1.4.dist-info/METADATA
cmany-0.1.4.dist-info/WHEEL
cmany-0.1.4.dist-info/entry_points.txt
cmany-0.1.4.dist-info/namespace_packages.txt
cmany-0.1.4.dist-info/top_level.txt
cmany-0.1.4.dist-info/RECORD
