Metadata-Version: 2.1
Name: cmany
Version: 0.1.4
Summary: CMake build tree batching tool
Home-page: https://github.com/biojppm/cmany
Author: Joao Paulo Magalhaes
Author-email: dev@jpmag.me
License: License :: OSI Approved :: MIT License
Download-URL: https://github.com/biojppm/cmany
Keywords: cmake,c++,c
Platform: UNKNOWN
Classifier: License :: OSI Approved :: MIT License
Classifier: Intended Audience :: Developers
Classifier: Development Status :: 3 - Alpha
Classifier: Programming Language :: Python :: 3.6
Classifier: Programming Language :: Python :: 3.7
Classifier: Programming Language :: Python :: 3.8
Classifier: Programming Language :: C
Classifier: Programming Language :: C++
Classifier: Topic :: Software Development :: Build Tools
Classifier: Topic :: Software Development :: Compilers
Classifier: Topic :: Software Development :: Libraries :: Python Modules
Classifier: Topic :: Utilities
Requires-Dist: ruamel.yaml (>=0.15.0)
Requires-Dist: colorama
Requires-Dist: argcomplete
Requires-Dist: dill
Requires-Dist: python-dateutil
